fastexec/VERSION
fastexec/__init__.py
fastexec/_dep.py
fastexec/_exec.py
fastexec/utils/__init__.py
fastexec/utils/convert.py
fastexec/utils/coro.py
fastexec/utils/graph.py
fastexec/version.py
fastexec-0.5.0.dist-info/LICENSE
fastexec-0.5.0.dist-info/METADATA
fastexec-0.5.0.dist-info/WHEEL
fastexec-0.5.0.dist-info/RECORD
